tfbi_theory/__init__.py
tfbi_theory/defaults.py
tfbi_theory/errors.py
tfbi_theory/tfbi_theory_manager.py
tfbi_theory/algebra/__init__.py
tfbi_theory/algebra/disprel.py
tfbi_theory/algebra/disprel_A.py
tfbi_theory/algebra/disprel_B.py
tfbi_theory/algebra/disprel_C.py
tfbi_theory/algebra/disprel_Cmns.py
tfbi_theory/algebra/disprel_E.py
tfbi_theory/algebra/inputs.py
tfbi_theory/algebra/vars.py
tfbi_theory/tools/__init__.py
tfbi_theory/tools/grids.py
tfbi_theory/tools/imports.py
tfbi_theory/tools/properties.py
tfbi_theory/tools/pytools.py
tfbi_theory/tools/sentinels.py
tfbi_theory/tools/timing.py
tfbi_theory/tools/xarrays.py
tfbi_theory-2025.6.0.dist-info/LICENSE
tfbi_theory-2025.6.0.dist-info/WHEEL
tfbi_theory-2025.6.0.dist-info/METADATA
tfbi_theory-2025.6.0.dist-info/RECORD
