Metadata-Version: 2.1
Name: tfbi_theory
Version: 2025.6.0
Summary: Solving the linear theory of the Thermal Farley-Buneman Instability (TFBI).
Author-email: Sam Evans <sevans7@bu.edu>
Requires-Python: >=3.9
Requires-Dist: xarray >= 2024.7.0
Requires-Dist: IPython
Requires-Dist: SymSolver
Project-URL: source-code, https://gitlab.com/Sevans7/tfbi_theory
